mythic/oobclient/__init__.py
mythic/oobclient/api_client.py
mythic/oobclient/client.py
mythic/oobclient/config.py
mythic/oobclient/errors.py
mythic/oobclient/port_forwarder.py
mythic/oobclient/raw_terminal.py
mythic/oobclient/terminal_emulator.py
mythic/oobclient/websocket.py
mythic/oobclient/websocket_terminal.py
mythic_oobclient-1.2.1.dist-info/METADATA
mythic_oobclient-1.2.1.dist-info/WHEEL
mythic_oobclient-1.2.1.dist-info/entry_points.txt
mythic_oobclient-1.2.1.dist-info/top_level.txt
mythic_oobclient-1.2.1.dist-info/RECORD
